{"v":"5.4.1","fr":30,"ip":0,"op":71,"w":500,"h":500,"nm":"eye","ddd":0,"assets":[],"layers":[{"ddd":0,"ind":1,"ty":4,"nm":"ZGVhZA==","sr":1,"ks":{"o":{"a":0,"k":100,"ix":11,"x":"var $bm_rt;\n$bm_rt = thisComp.layer('Null 4').effect('opacity')('Slider');"},"r":{"a":0,"k":0,"ix":10},"p":{"a":0,"k":[308.55,108.655,0],"ix":2},"a":{"a":0,"k":[58.55,-141.345,0],"ix":1},"s":{"a":0,"k":[100,100,100],"ix":6}},"ao":0,"shapes":[{"ty":"gr","it":[{"ind":0,"ty":"sh","ix":1,"ks":{"a":0,"k":{"i":[[0,0],[0,0]],"o":[[0,0],[0,0]],"v":[[82.81,-199.91],[34.29,-82.78]],"c":false},"ix":2},"nm":"Path 1","mn":"ADBE Vector Shape - Group","hd":false},{"ty":"st","c":{"a":0,"k":[0.274509817362,0.627451002598,0.960784316063,1],"ix":3},"o":{"a":0,"k":100,"ix":4},"w":{"a":0,"k":13,"ix":5,"x":"var $bm_rt;\n$bm_rt = thisComp.layer('Null 4').effect('side width')('Slider');"},"lc":1,"lj":1,"ml":10,"ml2":{"a":0,"k":10,"ix":8},"nm":".anim-main","mn":"ADBE Vector Graphic - Stroke","hd":false,"cl":"anim-main"},{"ty":"tm","s":{"a":0,"k":100,"ix":1},"e":{"a":0,"k":0,"ix":2,"x":"var $bm_rt;\n$bm_rt = sub(100, thisComp.layer('Null 4').effect('side')('Slider'));"},"o":{"a":0,"k":0,"ix":3},"m":1,"ix":3,"nm":"Trim Paths 1","mn":"ADBE Vector Filter - Trim","hd":false},{"ty":"tr","p":{"a":0,"k":[0,0],"ix":2},"a":{"a":0,"k":[0,0],"ix":1},"s":{"a":0,"k":[100,100],"ix":3},"r":{"a":0,"k":0,"ix":6},"o":{"a":0,"k":100,"ix":7},"sk":{"a":0,"k":0,"ix":4},"sa":{"a":0,"k":0,"ix":5},"nm":"Transform"}],"nm":"Group 1","np":3,"cix":2,"ix":1,"mn":"ADBE Vector Group","hd":false}],"ip":0,"op":321,"st":0,"bm":0},{"ddd":0,"ind":2,"ty":4,"nm":"b2Rpbg==","sr":1,"ks":{"o":{"a":0,"k":100,"ix":11,"x":"var $bm_rt;\n$bm_rt = thisComp.layer('Null 4').effect('opacity')('Slider');"},"r":{"a":0,"k":0,"ix":10},"p":{"a":0,"k":[361.91,138.09,0],"ix":2},"a":{"a":0,"k":[111.91,-111.91,0],"ix":1},"s":{"a":0,"k":[100,100,100],"ix":6}},"ao":0,"shapes":[{"ty":"gr","it":[{"ind":0,"ty":"sh","ix":1,"ks":{"a":0,"k":{"i":[[0,0],[0,0]],"o":[[0,0],[0,0]],"v":[[153.01,-153.01],[70.81,-70.81]],"c":false},"ix":2},"nm":"Path 1","mn":"ADBE Vector Shape - Group","hd":false},{"ty":"st","c":{"a":0,"k":[0.274509817362,0.627451002598,0.960784316063,1],"ix":3},"o":{"a":0,"k":100,"ix":4},"w":{"a":0,"k":13,"ix":5,"x":"var $bm_rt;\n$bm_rt = thisComp.layer('Null 4').effect('side width')('Slider');"},"lc":1,"lj":1,"ml":10,"ml2":{"a":0,"k":10,"ix":8},"nm":".anim-main","mn":"ADBE Vector Graphic - Stroke","hd":false,"cl":"anim-main"},{"ty":"tm","s":{"a":0,"k":100,"ix":1},"e":{"a":0,"k":0,"ix":2,"x":"var $bm_rt;\n$bm_rt = sub(100, thisComp.layer('Null 4').effect('side')('Slider'));"},"o":{"a":0,"k":0,"ix":3},"m":1,"ix":3,"nm":"Trim Paths 1","mn":"ADBE Vector Filter - Trim","hd":false},{"ty":"tr","p":{"a":0,"k":[0,0],"ix":2},"a":{"a":0,"k":[0,0],"ix":1},"s":{"a":0,"k":[100,100],"ix":3},"r":{"a":0,"k":0,"ix":6},"o":{"a":0,"k":100,"ix":7},"sk":{"a":0,"k":0,"ix":4},"sa":{"a":0,"k":0,"ix":5},"nm":"Transform"}],"nm":"Group 1","np":3,"cix":2,"ix":1,"mn":"ADBE Vector Group","hd":false}],"ip":0,"op":321,"st":0,"bm":0},{"ddd":0,"ind":3,"ty":4,"nm":"emVuZw==","sr":1,"ks":{"o":{"a":0,"k":100,"ix":11,"x":"var $bm_rt;\n$bm_rt = thisComp.layer('Null 4').effect('opacity')('Slider');"},"r":{"a":0,"k":0,"ix":10},"p":{"a":0,"k":[404.975,185.805,0],"ix":2},"a":{"a":0,"k":[154.975,-64.195,0],"ix":1},"s":{"a":0,"k":[100,100,100],"ix":6}},"ao":0,"shapes":[{"ty":"gr","it":[{"ind":0,"ty":"sh","ix":1,"ks":{"a":0,"k":{"i":[[0,0],[0,0]],"o":[[0,0],[0,0]],"v":[[199.91,-82.81],[110.04,-45.58]],"c":false},"ix":2},"nm":"Path 1","mn":"ADBE Vector Shape - Group","hd":false},{"ty":"st","c":{"a":0,"k":[0.274509817362,0.627451002598,0.960784316063,1],"ix":3},"o":{"a":0,"k":100,"ix":4},"w":{"a":0,"k":13,"ix":5,"x":"var $bm_rt;\n$bm_rt = thisComp.layer('Null 4').effect('side width')('Slider');"},"lc":1,"lj":1,"ml":10,"ml2":{"a":0,"k":10,"ix":8},"nm":".anim-main","mn":"ADBE Vector Graphic - Stroke","hd":false,"cl":"anim-main"},{"ty":"tm","s":{"a":0,"k":100,"ix":1},"e":{"a":0,"k":0,"ix":2,"x":"var $bm_rt;\n$bm_rt = sub(100, thisComp.layer('Null 4').effect('side')('Slider'));"},"o":{"a":0,"k":0,"ix":3},"m":1,"ix":3,"nm":"Trim Paths 1","mn":"ADBE Vector Filter - Trim","hd":false},{"ty":"tr","p":{"a":0,"k":[0,0],"ix":2},"a":{"a":0,"k":[0,0],"ix":1},"s":{"a":0,"k":[100,100],"ix":3},"r":{"a":0,"k":0,"ix":6},"o":{"a":0,"k":100,"ix":7},"sk":{"a":0,"k":0,"ix":4},"sa":{"a":0,"k":0,"ix":5},"nm":"Transform"}],"nm":"Group 1","np":3,"cix":2,"ix":1,"mn":"ADBE Vector Group","hd":false}],"ip":0,"op":321,"st":0,"bm":0},{"ddd":0,"ind":4,"ty":4,"nm":"Z29vZA==","sr":1,"ks":{"o":{"a":0,"k":100,"ix":11,"x":"var $bm_rt;\n$bm_rt = thisComp.layer('Null 4').effect('opacity')('Slider');"},"r":{"a":0,"k":0,"ix":10},"p":{"a":0,"k":[431.77,250,0],"ix":2},"a":{"a":0,"k":[181.77,0,0],"ix":1},"s":{"a":0,"k":[100,100,100],"ix":6}},"ao":0,"shapes":[{"ty":"gr","it":[{"ind":0,"ty":"sh","ix":1,"ks":{"a":0,"k":{"i":[[0,0],[0,0]],"o":[[0,0],[0,0]],"v":[[216.38,0],[147.16,0]],"c":false},"ix":2},"nm":"Path 1","mn":"ADBE Vector Shape - Group","hd":false},{"ty":"st","c":{"a":0,"k":[0.274509817362,0.627451002598,0.960784316063,1],"ix":3},"o":{"a":0,"k":100,"ix":4},"w":{"a":0,"k":13,"ix":5,"x":"var $bm_rt;\n$bm_rt = thisComp.layer('Null 4').effect('main width')('Slider');"},"lc":1,"lj":1,"ml":10,"ml2":{"a":0,"k":10,"ix":8},"nm":".anim-main","mn":"ADBE Vector Graphic - Stroke","hd":false,"cl":"anim-main"},{"ty":"tm","s":{"a":0,"k":100,"ix":1},"e":{"a":0,"k":0,"ix":2,"x":"var $bm_rt;\n$bm_rt = sub(100, thisComp.layer('Null 4').effect('main')('Slider'));"},"o":{"a":0,"k":0,"ix":3},"m":1,"ix":3,"nm":"Trim Paths 1","mn":"ADBE Vector Filter - Trim","hd":false},{"ty":"tr","p":{"a":0,"k":[0,0],"ix":2},"a":{"a":0,"k":[0,0],"ix":1},"s":{"a":0,"k":[100,100],"ix":3},"r":{"a":0,"k":0,"ix":6},"o":{"a":0,"k":100,"ix":7},"sk":{"a":0,"k":0,"ix":4},"sa":{"a":0,"k":0,"ix":5},"nm":"Transform"}],"nm":"Group 1","np":3,"cix":2,"ix":1,"mn":"ADBE Vector Group","hd":false}],"ip":0,"op":321,"st":0,"bm":0},{"ddd":0,"ind":5,"ty":4,"nm":"Z29uZQ==","sr":1,"ks":{"o":{"a":0,"k":100,"ix":11,"x":"var $bm_rt;\n$bm_rt = thisComp.layer('Null 4').effect('opacity')('Slider');"},"r":{"a":0,"k":0,"ix":10},"p":{"a":0,"k":[404.975,314.195,0],"ix":2},"a":{"a":0,"k":[154.975,64.195,0],"ix":1},"s":{"a":0,"k":[100,100,100],"ix":6}},"ao":0,"shapes":[{"ty":"gr","it":[{"ind":0,"ty":"sh","ix":1,"ks":{"a":0,"k":{"i":[[0,0],[0,0]],"o":[[0,0],[0,0]],"v":[[199.91,82.81],[110.04,45.58]],"c":false},"ix":2},"nm":"Path 1","mn":"ADBE Vector Shape - Group","hd":false},{"ty":"st","c":{"a":0,"k":[0.274509817362,0.627451002598,0.960784316063,1],"ix":3},"o":{"a":0,"k":100,"ix":4},"w":{"a":0,"k":13,"ix":5,"x":"var $bm_rt;\n$bm_rt = thisComp.layer('Null 4').effect('side width')('Slider');"},"lc":1,"lj":1,"ml":10,"ml2":{"a":0,"k":10,"ix":8},"nm":".anim-main","mn":"ADBE Vector Graphic - Stroke","hd":false,"cl":"anim-main"},{"ty":"tm","s":{"a":0,"k":100,"ix":1},"e":{"a":0,"k":0,"ix":2,"x":"var $bm_rt;\n$bm_rt = sub(100, thisComp.layer('Null 4').effect('side')('Slider'));"},"o":{"a":0,"k":0,"ix":3},"m":1,"ix":3,"nm":"Trim Paths 1","mn":"ADBE Vector Filter - Trim","hd":false},{"ty":"tr","p":{"a":0,"k":[0,0],"ix":2},"a":{"a":0,"k":[0,0],"ix":1},"s":{"a":0,"k":[100,100],"ix":3},"r":{"a":0,"k":0,"ix":6},"o":{"a":0,"k":100,"ix":7},"sk":{"a":0,"k":0,"ix":4},"sa":{"a":0,"k":0,"ix":5},"nm":"Transform"}],"nm":"Group 1","np":3,"cix":2,"ix":1,"mn":"ADBE Vector Group","hd":false}],"ip":0,"op":321,"st":0,"bm":0},{"ddd":0,"ind":6,"ty":4,"nm":"Layer 8","sr":1,"ks":{"o":{"a":0,"k":100,"ix":11,"x":"var $bm_rt;\n$bm_rt = thisComp.layer('Null 4').effect('opacity')('Slider');"},"r":{"a":0,"k":0,"ix":10},"p":{"a":0,"k":[361.91,361.91,0],"ix":2},"a":{"a":0,"k":[111.91,111.91,0],"ix":1},"s":{"a":0,"k":[100,100,100],"ix":6}},"ao":0,"shapes":[{"ty":"gr","it":[{"ind":0,"ty":"sh","ix":1,"ks":{"a":0,"k":{"i":[[0,0],[0,0]],"o":[[0,0],[0,0]],"v":[[153.01,153.01],[70.81,70.81]],"c":false},"ix":2},"nm":"Path 1","mn":"ADBE Vector Shape - Group","hd":false},{"ty":"st","c":{"a":0,"k":[0.274509817362,0.627451002598,0.960784316063,1],"ix":3},"o":{"a":0,"k":100,"ix":4},"w":{"a":0,"k":13,"ix":5,"x":"var $bm_rt;\n$bm_rt = thisComp.layer('Null 4').effect('side width')('Slider');"},"lc":1,"lj":1,"ml":10,"ml2":{"a":0,"k":10,"ix":8},"nm":".anim-main","mn":"ADBE Vector Graphic - Stroke","hd":false,"cl":"anim-main"},{"ty":"tm","s":{"a":0,"k":100,"ix":1},"e":{"a":0,"k":0,"ix":2,"x":"var $bm_rt;\n$bm_rt = sub(100, thisComp.layer('Null 4').effect('side')('Slider'));"},"o":{"a":0,"k":0,"ix":3},"m":1,"ix":3,"nm":"Trim Paths 1","mn":"ADBE Vector Filter - Trim","hd":false},{"ty":"tr","p":{"a":0,"k":[0,0],"ix":2},"a":{"a":0,"k":[0,0],"ix":1},"s":{"a":0,"k":[100,100],"ix":3},"r":{"a":0,"k":0,"ix":6},"o":{"a":0,"k":100,"ix":7},"sk":{"a":0,"k":0,"ix":4},"sa":{"a":0,"k":0,"ix":5},"nm":"Transform"}],"nm":"Group 1","np":3,"cix":2,"ix":1,"mn":"ADBE Vector Group","hd":false}],"ip":0,"op":321,"st":0,"bm":0},{"ddd":0,"ind":7,"ty":4,"nm":"Layer 10","sr":1,"ks":{"o":{"a":0,"k":100,"ix":11,"x":"var $bm_rt;\n$bm_rt = thisComp.layer('Null 4').effect('opacity')('Slider');"},"r":{"a":0,"k":0,"ix":10},"p":{"a":0,"k":[308.55,391.345,0],"ix":2},"a":{"a":0,"k":[58.55,141.345,0],"ix":1},"s":{"a":0,"k":[100,100,100],"ix":6}},"ao":0,"shapes":[{"ty":"gr","it":[{"ind":0,"ty":"sh","ix":1,"ks":{"a":0,"k":{"i":[[0,0],[0,0]],"o":[[0,0],[0,0]],"v":[[82.81,199.91],[34.29,82.78]],"c":false},"ix":2},"nm":"Path 1","mn":"ADBE Vector Shape - Group","hd":false},{"ty":"st","c":{"a":0,"k":[0.274509817362,0.627451002598,0.960784316063,1],"ix":3},"o":{"a":0,"k":100,"ix":4},"w":{"a":0,"k":13,"ix":5,"x":"var $bm_rt;\n$bm_rt = thisComp.layer('Null 4').effect('side width')('Slider');"},"lc":1,"lj":1,"ml":10,"ml2":{"a":0,"k":10,"ix":8},"nm":".anim-main","mn":"ADBE Vector Graphic - Stroke","hd":false,"cl":"anim-main"},{"ty":"tm","s":{"a":0,"k":100,"ix":1},"e":{"a":0,"k":0,"ix":2,"x":"var $bm_rt;\n$bm_rt = sub(100, thisComp.layer('Null 4').effect('side')('Slider'));"},"o":{"a":0,"k":0,"ix":3},"m":1,"ix":3,"nm":"Trim Paths 1","mn":"ADBE Vector Filter - Trim","hd":false},{"ty":"tr","p":{"a":0,"k":[0,0],"ix":2},"a":{"a":0,"k":[0,0],"ix":1},"s":{"a":0,"k":[100,100],"ix":3},"r":{"a":0,"k":0,"ix":6},"o":{"a":0,"k":100,"ix":7},"sk":{"a":0,"k":0,"ix":4},"sa":{"a":0,"k":0,"ix":5},"nm":"Transform"}],"nm":"Group 1","np":3,"cix":2,"ix":1,"mn":"ADBE Vector Group","hd":false}],"ip":0,"op":321,"st":0,"bm":0},{"ddd":0,"ind":8,"ty":4,"nm":"Layer 7","sr":1,"ks":{"o":{"a":0,"k":100,"ix":11,"x":"var $bm_rt;\n$bm_rt = thisComp.layer('Null 4').effect('opacity')('Slider');"},"r":{"a":0,"k":0,"ix":10},"p":{"a":0,"k":[250,401.325,0],"ix":2},"a":{"a":0,"k":[0,151.325,0],"ix":1},"s":{"a":0,"k":[100,100,100],"ix":6}},"ao":0,"shapes":[{"ty":"gr","it":[{"ind":0,"ty":"sh","ix":1,"ks":{"a":0,"k":{"i":[[0,0],[0,0]],"o":[[0,0],[0,0]],"v":[[0,216.38],[0,86.27]],"c":false},"ix":2},"nm":"Path 1","mn":"ADBE Vector Shape - Group","hd":false},{"ty":"st","c":{"a":0,"k":[0.274509817362,0.627451002598,0.960784316063,1],"ix":3},"o":{"a":0,"k":100,"ix":4},"w":{"a":0,"k":13,"ix":5,"x":"var $bm_rt;\n$bm_rt = thisComp.layer('Null 4').effect('main width')('Slider');"},"lc":1,"lj":1,"ml":10,"ml2":{"a":0,"k":10,"ix":8},"nm":".anim-main","mn":"ADBE Vector Graphic - Stroke","hd":false,"cl":"anim-main"},{"ty":"tm","s":{"a":0,"k":100,"ix":1},"e":{"a":0,"k":0,"ix":2,"x":"var $bm_rt;\n$bm_rt = sub(100, thisComp.layer('Null 4').effect('main')('Slider'));"},"o":{"a":0,"k":0,"ix":3},"m":1,"ix":3,"nm":"Trim Paths 1","mn":"ADBE Vector Filter - Trim","hd":false},{"ty":"tr","p":{"a":0,"k":[0,0],"ix":2},"a":{"a":0,"k":[0,0],"ix":1},"s":{"a":0,"k":[100,100],"ix":3},"r":{"a":0,"k":0,"ix":6},"o":{"a":0,"k":100,"ix":7},"sk":{"a":0,"k":0,"ix":4},"sa":{"a":0,"k":0,"ix":5},"nm":"Transform"}],"nm":"Group 1","np":3,"cix":2,"ix":1,"mn":"ADBE Vector Group","hd":false}],"ip":0,"op":321,"st":0,"bm":0},{"ddd":0,"ind":9,"ty":4,"nm":"Layer 13","sr":1,"ks":{"o":{"a":0,"k":100,"ix":11,"x":"var $bm_rt;\n$bm_rt = thisComp.layer('Null 4').effect('opacity')('Slider');"},"r":{"a":0,"k":0,"ix":10},"p":{"a":0,"k":[191.45,391.345,0],"ix":2},"a":{"a":0,"k":[-58.55,141.345,0],"ix":1},"s":{"a":0,"k":[100,100,100],"ix":6}},"ao":0,"shapes":[{"ty":"gr","it":[{"ind":0,"ty":"sh","ix":1,"ks":{"a":0,"k":{"i":[[0,0],[0,0]],"o":[[0,0],[0,0]],"v":[[-82.81,199.91],[-34.29,82.78]],"c":false},"ix":2},"nm":"Path 1","mn":"ADBE Vector Shape - Group","hd":false},{"ty":"st","c":{"a":0,"k":[0.274509817362,0.627451002598,0.960784316063,1],"ix":3},"o":{"a":0,"k":100,"ix":4},"w":{"a":0,"k":13,"ix":5,"x":"var $bm_rt;\n$bm_rt = thisComp.layer('Null 4').effect('side width')('Slider');"},"lc":1,"lj":1,"ml":10,"ml2":{"a":0,"k":10,"ix":8},"nm":".anim-main","mn":"ADBE Vector Graphic - Stroke","hd":false,"cl":"anim-main"},{"ty":"tm","s":{"a":0,"k":100,"ix":1},"e":{"a":0,"k":0,"ix":2,"x":"var $bm_rt;\n$bm_rt = sub(100, thisComp.layer('Null 4').effect('side')('Slider'));"},"o":{"a":0,"k":0,"ix":3},"m":1,"ix":3,"nm":"Trim Paths 1","mn":"ADBE Vector Filter - Trim","hd":false},{"ty":"tr","p":{"a":0,"k":[0,0],"ix":2},"a":{"a":0,"k":[0,0],"ix":1},"s":{"a":0,"k":[100,100],"ix":3},"r":{"a":0,"k":0,"ix":6},"o":{"a":0,"k":100,"ix":7},"sk":{"a":0,"k":0,"ix":4},"sa":{"a":0,"k":0,"ix":5},"nm":"Transform"}],"nm":"Group 1","np":3,"cix":2,"ix":1,"mn":"ADBE Vector Group","hd":false}],"ip":0,"op":321,"st":0,"bm":0},{"ddd":0,"ind":10,"ty":4,"nm":"Layer 12","sr":1,"ks":{"o":{"a":0,"k":100,"ix":11,"x":"var $bm_rt;\n$bm_rt = thisComp.layer('Null 4').effect('opacity')('Slider');"},"r":{"a":0,"k":0,"ix":10},"p":{"a":0,"k":[138.09,361.91,0],"ix":2},"a":{"a":0,"k":[-111.91,111.91,0],"ix":1},"s":{"a":0,"k":[100,100,100],"ix":6}},"ao":0,"shapes":[{"ty":"gr","it":[{"ind":0,"ty":"sh","ix":1,"ks":{"a":0,"k":{"i":[[0,0],[0,0]],"o":[[0,0],[0,0]],"v":[[-153.01,153.01],[-70.81,70.81]],"c":false},"ix":2},"nm":"Path 1","mn":"ADBE Vector Shape - Group","hd":false},{"ty":"st","c":{"a":0,"k":[0.274509817362,0.627451002598,0.960784316063,1],"ix":3},"o":{"a":0,"k":100,"ix":4},"w":{"a":0,"k":13,"ix":5,"x":"var $bm_rt;\n$bm_rt = thisComp.layer('Null 4').effect('side width')('Slider');"},"lc":1,"lj":1,"ml":10,"ml2":{"a":0,"k":10,"ix":8},"nm":".anim-main","mn":"ADBE Vector Graphic - Stroke","hd":false,"cl":"anim-main"},{"ty":"tm","s":{"a":0,"k":100,"ix":1},"e":{"a":0,"k":0,"ix":2,"x":"var $bm_rt;\n$bm_rt = sub(100, thisComp.layer('Null 4').effect('side')('Slider'));"},"o":{"a":0,"k":0,"ix":3},"m":1,"ix":3,"nm":"Trim Paths 1","mn":"ADBE Vector Filter - Trim","hd":false},{"ty":"tr","p":{"a":0,"k":[0,0],"ix":2},"a":{"a":0,"k":[0,0],"ix":1},"s":{"a":0,"k":[100,100],"ix":3},"r":{"a":0,"k":0,"ix":6},"o":{"a":0,"k":100,"ix":7},"sk":{"a":0,"k":0,"ix":4},"sa":{"a":0,"k":0,"ix":5},"nm":"Transform"}],"nm":"Group 1","np":3,"cix":2,"ix":1,"mn":"ADBE Vector Group","hd":false}],"ip":0,"op":321,"st":0,"bm":0},{"ddd":0,"ind":11,"ty":4,"nm":"Layer 14","sr":1,"ks":{"o":{"a":0,"k":100,"ix":11,"x":"var $bm_rt;\n$bm_rt = thisComp.layer('Null 4').effect('opacity')('Slider');"},"r":{"a":0,"k":0,"ix":10},"p":{"a":0,"k":[95.025,314.195,0],"ix":2},"a":{"a":0,"k":[-154.975,64.195,0],"ix":1},"s":{"a":0,"k":[100,100,100],"ix":6}},"ao":0,"shapes":[{"ty":"gr","it":[{"ind":0,"ty":"sh","ix":1,"ks":{"a":0,"k":{"i":[[0,0],[0,0]],"o":[[0,0],[0,0]],"v":[[-199.91,82.81],[-110.04,45.58]],"c":false},"ix":2},"nm":"Path 1","mn":"ADBE Vector Shape - Group","hd":false},{"ty":"st","c":{"a":0,"k":[0.274509817362,0.627451002598,0.960784316063,1],"ix":3},"o":{"a":0,"k":100,"ix":4},"w":{"a":0,"k":13,"ix":5,"x":"var $bm_rt;\n$bm_rt = thisComp.layer('Null 4').effect('side width')('Slider');"},"lc":1,"lj":1,"ml":10,"ml2":{"a":0,"k":10,"ix":8},"nm":".anim-main","mn":"ADBE Vector Graphic - Stroke","hd":false,"cl":"anim-main"},{"ty":"tm","s":{"a":0,"k":100,"ix":1},"e":{"a":0,"k":0,"ix":2,"x":"var $bm_rt;\n$bm_rt = sub(100, thisComp.layer('Null 4').effect('side')('Slider'));"},"o":{"a":0,"k":0,"ix":3},"m":1,"ix":3,"nm":"Trim Paths 1","mn":"ADBE Vector Filter - Trim","hd":false},{"ty":"tr","p":{"a":0,"k":[0,0],"ix":2},"a":{"a":0,"k":[0,0],"ix":1},"s":{"a":0,"k":[100,100],"ix":3},"r":{"a":0,"k":0,"ix":6},"o":{"a":0,"k":100,"ix":7},"sk":{"a":0,"k":0,"ix":4},"sa":{"a":0,"k":0,"ix":5},"nm":"Transform"}],"nm":"Group 1","np":3,"cix":2,"ix":1,"mn":"ADBE Vector Group","hd":false}],"ip":0,"op":321,"st":0,"bm":0},{"ddd":0,"ind":12,"ty":4,"nm":"Layer 11","sr":1,"ks":{"o":{"a":0,"k":100,"ix":11,"x":"var $bm_rt;\n$bm_rt = thisComp.layer('Null 4').effect('opacity')('Slider');"},"r":{"a":0,"k":0,"ix":10},"p":{"a":0,"k":[68.23,250,0],"ix":2},"a":{"a":0,"k":[-181.77,0,0],"ix":1},"s":{"a":0,"k":[100,100,100],"ix":6}},"ao":0,"shapes":[{"ty":"gr","it":[{"ind":0,"ty":"sh","ix":1,"ks":{"a":0,"k":{"i":[[0,0],[0,0]],"o":[[0,0],[0,0]],"v":[[-216.38,0],[-147.16,0]],"c":false},"ix":2},"nm":"Path 1","mn":"ADBE Vector Shape - Group","hd":false},{"ty":"st","c":{"a":0,"k":[0.274509817362,0.627451002598,0.960784316063,1],"ix":3},"o":{"a":0,"k":100,"ix":4},"w":{"a":0,"k":13,"ix":5,"x":"var $bm_rt;\n$bm_rt = thisComp.layer('Null 4').effect('main width')('Slider');"},"lc":1,"lj":1,"ml":10,"ml2":{"a":0,"k":10,"ix":8},"nm":".anim-main","mn":"ADBE Vector Graphic - Stroke","hd":false,"cl":"anim-main"},{"ty":"tm","s":{"a":0,"k":100,"ix":1},"e":{"a":0,"k":0,"ix":2,"x":"var $bm_rt;\n$bm_rt = sub(100, thisComp.layer('Null 4').effect('main')('Slider'));"},"o":{"a":0,"k":0,"ix":3},"m":1,"ix":3,"nm":"Trim Paths 1","mn":"ADBE Vector Filter - Trim","hd":false},{"ty":"tr","p":{"a":0,"k":[0,0],"ix":2},"a":{"a":0,"k":[0,0],"ix":1},"s":{"a":0,"k":[100,100],"ix":3},"r":{"a":0,"k":0,"ix":6},"o":{"a":0,"k":100,"ix":7},"sk":{"a":0,"k":0,"ix":4},"sa":{"a":0,"k":0,"ix":5},"nm":"Transform"}],"nm":"Group 1","np":3,"cix":2,"ix":1,"mn":"ADBE Vector Group","hd":false}],"ip":0,"op":321,"st":0,"bm":0},{"ddd":0,"ind":13,"ty":4,"nm":"Layer 17","sr":1,"ks":{"o":{"a":0,"k":100,"ix":11,"x":"var $bm_rt;\n$bm_rt = thisComp.layer('Null 4').effect('opacity')('Slider');"},"r":{"a":0,"k":0,"ix":10},"p":{"a":0,"k":[95.025,185.805,0],"ix":2},"a":{"a":0,"k":[-154.975,-64.195,0],"ix":1},"s":{"a":0,"k":[100,100,100],"ix":6}},"ao":0,"shapes":[{"ty":"gr","it":[{"ind":0,"ty":"sh","ix":1,"ks":{"a":0,"k":{"i":[[0,0],[0,0]],"o":[[0,0],[0,0]],"v":[[-199.91,-82.81],[-110.04,-45.58]],"c":false},"ix":2},"nm":"Path 1","mn":"ADBE Vector Shape - Group","hd":false},{"ty":"st","c":{"a":0,"k":[0.274509817362,0.627451002598,0.960784316063,1],"ix":3},"o":{"a":0,"k":100,"ix":4},"w":{"a":0,"k":13,"ix":5,"x":"var $bm_rt;\n$bm_rt = thisComp.layer('Null 4').effect('side width')('Slider');"},"lc":1,"lj":1,"ml":10,"ml2":{"a":0,"k":10,"ix":8},"nm":".anim-main","mn":"ADBE Vector Graphic - Stroke","hd":false,"cl":"anim-main"},{"ty":"tm","s":{"a":0,"k":100,"ix":1},"e":{"a":0,"k":0,"ix":2,"x":"var $bm_rt;\n$bm_rt = sub(100, thisComp.layer('Null 4').effect('side')('Slider'));"},"o":{"a":0,"k":0,"ix":3},"m":1,"ix":3,"nm":"Trim Paths 1","mn":"ADBE Vector Filter - Trim","hd":false},{"ty":"tr","p":{"a":0,"k":[0,0],"ix":2},"a":{"a":0,"k":[0,0],"ix":1},"s":{"a":0,"k":[100,100],"ix":3},"r":{"a":0,"k":0,"ix":6},"o":{"a":0,"k":100,"ix":7},"sk":{"a":0,"k":0,"ix":4},"sa":{"a":0,"k":0,"ix":5},"nm":"Transform"}],"nm":"Group 1","np":3,"cix":2,"ix":1,"mn":"ADBE Vector Group","hd":false}],"ip":0,"op":321,"st":0,"bm":0},{"ddd":0,"ind":14,"ty":4,"nm":"Layer 16","sr":1,"ks":{"o":{"a":0,"k":100,"ix":11,"x":"var $bm_rt;\n$bm_rt = thisComp.layer('Null 4').effect('opacity')('Slider');"},"r":{"a":0,"k":0,"ix":10},"p":{"a":0,"k":[138.09,138.09,0],"ix":2},"a":{"a":0,"k":[-111.91,-111.91,0],"ix":1},"s":{"a":0,"k":[100,100,100],"ix":6}},"ao":0,"shapes":[{"ty":"gr","it":[{"ind":0,"ty":"sh","ix":1,"ks":{"a":0,"k":{"i":[[0,0],[0,0]],"o":[[0,0],[0,0]],"v":[[-153.01,-153.01],[-70.81,-70.81]],"c":false},"ix":2},"nm":"Path 1","mn":"ADBE Vector Shape - Group","hd":false},{"ty":"st","c":{"a":0,"k":[0.274509817362,0.627451002598,0.960784316063,1],"ix":3},"o":{"a":0,"k":100,"ix":4},"w":{"a":0,"k":13,"ix":5,"x":"var $bm_rt;\n$bm_rt = thisComp.layer('Null 4').effect('side width')('Slider');"},"lc":1,"lj":1,"ml":10,"ml2":{"a":0,"k":10,"ix":8},"nm":".anim-main","mn":"ADBE Vector Graphic - Stroke","hd":false,"cl":"anim-main"},{"ty":"tm","s":{"a":0,"k":100,"ix":1},"e":{"a":0,"k":0,"ix":2,"x":"var $bm_rt;\n$bm_rt = sub(100, thisComp.layer('Null 4').effect('side')('Slider'));"},"o":{"a":0,"k":0,"ix":3},"m":1,"ix":3,"nm":"Trim Paths 1","mn":"ADBE Vector Filter - Trim","hd":false},{"ty":"tr","p":{"a":0,"k":[0,0],"ix":2},"a":{"a":0,"k":[0,0],"ix":1},"s":{"a":0,"k":[100,100],"ix":3},"r":{"a":0,"k":0,"ix":6},"o":{"a":0,"k":100,"ix":7},"sk":{"a":0,"k":0,"ix":4},"sa":{"a":0,"k":0,"ix":5},"nm":"Transform"}],"nm":"Group 1","np":3,"cix":2,"ix":1,"mn":"ADBE Vector Group","hd":false}],"ip":0,"op":321,"st":0,"bm":0},{"ddd":0,"ind":15,"ty":4,"nm":"Layer 18","sr":1,"ks":{"o":{"a":0,"k":100,"ix":11,"x":"var $bm_rt;\n$bm_rt = thisComp.layer('Null 4').effect('opacity')('Slider');"},"r":{"a":0,"k":0,"ix":10},"p":{"a":0,"k":[191.45,108.655,0],"ix":2},"a":{"a":0,"k":[-58.55,-141.345,0],"ix":1},"s":{"a":0,"k":[100,100,100],"ix":6}},"ao":0,"shapes":[{"ty":"gr","it":[{"ind":0,"ty":"sh","ix":1,"ks":{"a":0,"k":{"i":[[0,0],[0,0]],"o":[[0,0],[0,0]],"v":[[-82.81,-199.91],[-34.29,-82.78]],"c":false},"ix":2},"nm":"Path 1","mn":"ADBE Vector Shape - Group","hd":false},{"ty":"st","c":{"a":0,"k":[0.274509817362,0.627451002598,0.960784316063,1],"ix":3},"o":{"a":0,"k":100,"ix":4},"w":{"a":0,"k":13,"ix":5,"x":"var $bm_rt;\n$bm_rt = thisComp.layer('Null 4').effect('side width')('Slider');"},"lc":1,"lj":1,"ml":10,"ml2":{"a":0,"k":10,"ix":8},"nm":".anim-main","mn":"ADBE Vector Graphic - Stroke","hd":false,"cl":"anim-main"},{"ty":"tm","s":{"a":0,"k":100,"ix":1},"e":{"a":0,"k":0,"ix":2,"x":"var $bm_rt;\n$bm_rt = sub(100, thisComp.layer('Null 4').effect('side')('Slider'));"},"o":{"a":0,"k":0,"ix":3},"m":1,"ix":3,"nm":"Trim Paths 1","mn":"ADBE Vector Filter - Trim","hd":false},{"ty":"tr","p":{"a":0,"k":[0,0],"ix":2},"a":{"a":0,"k":[0,0],"ix":1},"s":{"a":0,"k":[100,100],"ix":3},"r":{"a":0,"k":0,"ix":6},"o":{"a":0,"k":100,"ix":7},"sk":{"a":0,"k":0,"ix":4},"sa":{"a":0,"k":0,"ix":5},"nm":"Transform"}],"nm":"Group 1","np":3,"cix":2,"ix":1,"mn":"ADBE Vector Group","hd":false}],"ip":0,"op":321,"st":0,"bm":0},{"ddd":0,"ind":16,"ty":4,"nm":"Layer 15","sr":1,"ks":{"o":{"a":0,"k":100,"ix":11,"x":"var $bm_rt;\n$bm_rt = thisComp.layer('Null 4').effect('opacity')('Slider');"},"r":{"a":0,"k":0,"ix":10},"p":{"a":0,"k":[250,98.675,0],"ix":2},"a":{"a":0,"k":[0,-151.325,0],"ix":1},"s":{"a":0,"k":[100,100,100],"ix":6}},"ao":0,"shapes":[{"ty":"gr","it":[{"ind":0,"ty":"sh","ix":1,"ks":{"a":0,"k":{"i":[[0,0],[0,0]],"o":[[0,0],[0,0]],"v":[[0,-216.38],[0,-86.27]],"c":false},"ix":2},"nm":"Path 1","mn":"ADBE Vector Shape - Group","hd":false},{"ty":"st","c":{"a":0,"k":[0.274509817362,0.627451002598,0.960784316063,1],"ix":3},"o":{"a":0,"k":100,"ix":4},"w":{"a":0,"k":13,"ix":5,"x":"var $bm_rt;\n$bm_rt = thisComp.layer('Null 4').effect('main width')('Slider');"},"lc":1,"lj":1,"ml":10,"ml2":{"a":0,"k":10,"ix":8},"nm":".anim-main","mn":"ADBE Vector Graphic - Stroke","hd":false,"cl":"anim-main"},{"ty":"tm","s":{"a":0,"k":100,"ix":1},"e":{"a":0,"k":0,"ix":2,"x":"var $bm_rt;\n$bm_rt = sub(100, thisComp.layer('Null 4').effect('main')('Slider'));"},"o":{"a":0,"k":0,"ix":3},"m":1,"ix":3,"nm":"Trim Paths 1","mn":"ADBE Vector Filter - Trim","hd":false},{"ty":"tr","p":{"a":0,"k":[0,0],"ix":2},"a":{"a":0,"k":[0,0],"ix":1},"s":{"a":0,"k":[100,100],"ix":3},"r":{"a":0,"k":0,"ix":6},"o":{"a":0,"k":100,"ix":7},"sk":{"a":0,"k":0,"ix":4},"sa":{"a":0,"k":0,"ix":5},"nm":"Transform"}],"nm":"Group 1","np":3,"cix":2,"ix":1,"mn":"ADBE Vector Group","hd":false}],"ip":0,"op":321,"st":0,"bm":0},{"ddd":0,"ind":17,"ty":4,"nm":"pupil 2","sr":1,"ks":{"o":{"a":1,"k":[{"i":{"x":[0.1],"y":[1]},"o":{"x":[0.9],"y":[0]},"n":["0p1_1_0p9_0"],"t":60,"s":[100],"e":[0]},{"t":69}],"ix":11},"r":{"a":0,"k":90,"ix":10},"p":{"a":0,"k":[250,250,0],"ix":2},"a":{"a":0,"k":[0,0,0],"ix":1},"s":{"a":0,"k":[100,100,100],"ix":6}},"ao":0,"shapes":[{"ty":"gr","it":[{"ind":0,"ty":"sh","ix":1,"ks":{"a":0,"k":{"i":[[-17.999,0],[0,-17.999],[17.999,0],[0,17.999],[-17.999,0]],"o":[[17.999,0],[0,17.999],[-17.999,0],[0,-17.999],[17.999,0]],"v":[[0,-32.59],[32.59,0],[0,32.59],[-32.59,0],[0,-32.59]],"c":false},"ix":2},"nm":"Path 1","mn":"ADBE Vector Shape - Group","hd":false},{"ty":"st","c":{"a":0,"k":[0.274509803922,0.627450980392,0.960784313725,1],"ix":3},"o":{"a":0,"k":100,"ix":4},"w":{"a":1,"k":[{"i":{"x":[0.1],"y":[1]},"o":{"x":[0.9],"y":[0]},"n":["0p1_1_0p9_0"],"t":59,"s":[38],"e":[0]},{"t":63}],"ix":5},"lc":1,"lj":1,"ml":10,"ml2":{"a":0,"k":10,"ix":8},"nm":".anim-main","mn":"ADBE Vector Graphic - Stroke","hd":false,"cl":"anim-main"},{"ty":"tr","p":{"a":0,"k":[0,0],"ix":2},"a":{"a":0,"k":[0,0],"ix":1},"s":{"a":0,"k":[100,100],"ix":3},"r":{"a":0,"k":0,"ix":6},"o":{"a":0,"k":100,"ix":7},"sk":{"a":0,"k":0,"ix":4},"sa":{"a":0,"k":0,"ix":5},"nm":"Transform"}],"nm":"Group 1","np":2,"cix":2,"ix":1,"mn":"ADBE Vector Group","hd":false},{"ty":"tm","s":{"a":1,"k":[{"i":{"x":[0.807],"y":[0.398]},"o":{"x":[0.507],"y":[0]},"n":["0p807_0p398_0p507_0"],"t":9,"s":[0],"e":[14.796]},{"i":{"x":[0.663],"y":[97350.183]},"o":{"x":[0.33],"y":[-108337.32]},"n":["0p663_97350p183_0p33_-108337p32"],"t":13,"s":[14.796],"e":[14.796]},{"t":14,"s":[14.796],"h":1},{"i":{"x":[0.1],"y":[1]},"o":{"x":[0.88],"y":[0.14]},"n":["0p1_1_0p88_0p14"],"t":50,"s":[14.796],"e":[100]},{"t":71}],"ix":1},"e":{"a":0,"k":0,"ix":2},"o":{"a":1,"k":[{"i":{"x":[0.833],"y":[0.833]},"o":{"x":[0.167],"y":[0.167]},"n":["0p833_0p833_0p167_0p167"],"t":8,"s":[0],"e":[360]},{"i":{"x":[0.833],"y":[0.833]},"o":{"x":[0.167],"y":[0.167]},"n":["0p833_0p833_0p167_0p167"],"t":38.731,"s":[360],"e":[720]},{"t":71}],"ix":3},"m":1,"ix":2,"nm":"Trim Paths 1","mn":"ADBE Vector Filter - Trim","hd":false}],"ip":0,"op":321,"st":0,"bm":0},{"ddd":0,"ind":18,"ty":4,"nm":"pupil","sr":1,"ks":{"o":{"a":1,"k":[{"i":{"x":[0.833],"y":[0.833]},"o":{"x":[0.167],"y":[0.167]},"n":["0p833_0p833_0p167_0p167"],"t":61,"s":[100],"e":[0]},{"t":62}],"ix":11},"r":{"a":0,"k":90,"ix":10},"p":{"a":0,"k":[250,250,0],"ix":2},"a":{"a":0,"k":[0,0,0],"ix":1},"s":{"a":0,"k":[100,100,100],"ix":6}},"ao":0,"shapes":[{"ty":"gr","it":[{"ind":0,"ty":"sh","ix":1,"ks":{"a":0,"k":{"i":[[-17.999,0],[0,-17.999],[17.999,0],[0,17.999],[-17.999,0]],"o":[[17.999,0],[0,17.999],[-17.999,0],[0,-17.999],[17.999,0]],"v":[[0,-32.59],[32.59,0],[0,32.59],[-32.59,0],[0,-32.59]],"c":false},"ix":2},"nm":"Path 1","mn":"ADBE Vector Shape - Group","hd":false},{"ty":"st","c":{"a":0,"k":[0.070588235294,0.074509803922,0.086274509804,1],"ix":3},"o":{"a":0,"k":100,"ix":4},"w":{"a":1,"k":[{"i":{"x":[0.1],"y":[1]},"o":{"x":[0.9],"y":[0]},"n":["0p1_1_0p9_0"],"t":59,"s":[36],"e":[0]},{"t":63}],"ix":5},"lc":1,"lj":1,"ml":10,"ml2":{"a":0,"k":10,"ix":8},"nm":".anim-mask","mn":"ADBE Vector Graphic - Stroke","hd":false,"cl":"anim-mask"},{"ty":"tr","p":{"a":0,"k":[0,0],"ix":2},"a":{"a":0,"k":[0,0],"ix":1},"s":{"a":0,"k":[100,100],"ix":3},"r":{"a":0,"k":0,"ix":6},"o":{"a":0,"k":100,"ix":7},"sk":{"a":0,"k":0,"ix":4},"sa":{"a":0,"k":0,"ix":5},"nm":"Transform"}],"nm":"Group 1","np":2,"cix":2,"ix":1,"mn":"ADBE Vector Group","hd":false},{"ty":"tm","s":{"a":0,"k":100,"ix":1},"e":{"a":0,"k":0,"ix":2},"o":{"a":0,"k":0,"ix":3},"m":1,"ix":2,"nm":"Trim Paths 1","mn":"ADBE Vector Filter - Trim","hd":false}],"ip":0,"op":321,"st":0,"bm":0},{"ddd":0,"ind":19,"ty":4,"nm":"eye","sr":1,"ks":{"o":{"a":0,"k":100,"ix":11},"r":{"a":0,"k":0,"ix":10},"p":{"a":0,"k":[250,250,0],"ix":2},"a":{"a":0,"k":[0,0,0],"ix":1},"s":{"a":0,"k":[100,100,100],"ix":6}},"ao":0,"shapes":[{"ty":"gr","it":[{"ind":0,"ty":"sh","ix":1,"ks":{"a":1,"k":[{"i":{"x":0.1,"y":1},"o":{"x":0.88,"y":0.14},"n":"0p1_1_0p88_0p14","t":4,"s":[{"i":[[54.617,0],[0,0],[-22.692,0],[-55.899,0],[0,0],[0,0],[50.148,0]],"o":[[0,0],[50.924,0],[50.148,0],[0,0],[0,0],[-45.642,0],[-50.148,0]],"v":[[-128.693,0],[-128.693,0],[0,0],[128.693,0],[128.693,0],[128.693,0],[0,0]],"c":true}],"e":[{"i":[[28.202,50.066],[0,0],[-22.692,0],[-28.202,-50.066],[0,0],[0,0],[50.148,0]],"o":[[0,0],[38.886,-69.034],[50.148,0],[0,0],[0,0],[-28.202,50.066],[-50.148,0]],"v":[[-128.693,0],[-128.693,0],[0,-75.447],[128.693,0],[128.693,0],[128.693,0],[0,75.447]],"c":true}]},{"i":{"x":0.1,"y":1},"o":{"x":0.167,"y":0},"n":"0p1_1_0p167_0","t":14,"s":[{"i":[[28.202,50.066],[0,0],[-22.692,0],[-28.202,-50.066],[0,0],[0,0],[50.148,0]],"o":[[0,0],[38.886,-69.034],[50.148,0],[0,0],[0,0],[-28.202,50.066],[-50.148,0]],"v":[[-128.693,0],[-128.693,0],[0,-75.447],[128.693,0],[128.693,0],[128.693,0],[0,75.447]],"c":true}],"e":[{"i":[[28.202,50.066],[0,0],[-22.692,0],[-28.202,-50.066],[0,0],[0,0],[50.148,0]],"o":[[0,0],[38.886,-69.034],[50.148,0],[0,0],[0,0],[-28.202,50.066],[-50.148,0]],"v":[[-128.693,0],[-128.693,0],[0,-75.447],[128.693,0],[128.693,0],[128.693,0],[0,75.447]],"c":true}]},{"i":{"x":0.1,"y":1},"o":{"x":0.9,"y":0},"n":"0p1_1_0p9_0","t":59,"s":[{"i":[[28.202,50.066],[0,0],[-22.692,0],[-28.202,-50.066],[0,0],[0,0],[50.148,0]],"o":[[0,0],[38.886,-69.034],[50.148,0],[0,0],[0,0],[-28.202,50.066],[-50.148,0]],"v":[[-128.693,0],[-128.693,0],[0,-75.447],[128.693,0],[128.693,0],[128.693,0],[0,75.447]],"c":true}],"e":[{"i":[[54.617,0],[0,0],[-22.692,0],[-55.899,0],[0,0],[0,0],[50.148,0]],"o":[[0,0],[50.924,0],[50.148,0],[0,0],[0,0],[-45.642,0],[-50.148,0]],"v":[[-128.693,0],[-128.693,0],[0,0],[128.693,0],[128.693,0],[128.693,0],[0,0]],"c":true}]},{"t":66}],"ix":2},"nm":"Path 1","mn":"ADBE Vector Shape - Group","hd":false},{"ty":"fl","c":{"a":0,"k":[0.274509817362,0.627451002598,0.960784316063,1],"ix":4},"o":{"a":0,"k":100,"ix":5},"r":1,"nm":".anim-main","mn":"ADBE Vector Graphic - Fill","hd":false,"cl":"anim-main"},{"ty":"st","c":{"a":0,"k":[0.274509803922,0.627450980392,0.960784313725,1],"ix":3},"o":{"a":0,"k":100,"ix":4},"w":{"a":0,"k":3,"ix":5},"lc":2,"lj":2,"nm":".anim-main","mn":"ADBE Vector Graphic - Stroke","hd":false,"cl":"anim-main"},{"ty":"tr","p":{"a":0,"k":[0,0],"ix":2},"a":{"a":0,"k":[0,0],"ix":1},"s":{"a":0,"k":[100,100],"ix":3},"r":{"a":0,"k":0,"ix":6},"o":{"a":1,"k":[{"i":{"x":[0.24],"y":[1]},"o":{"x":[0.76],"y":[0]},"n":["0p24_1_0p76_0"],"t":0,"s":[0],"e":[100]},{"i":{"x":[0.24],"y":[1]},"o":{"x":[0.76],"y":[0]},"n":["0p24_1_0p76_0"],"t":7,"s":[100],"e":[100]},{"i":{"x":[0.24],"y":[1]},"o":{"x":[0.76],"y":[0]},"n":["0p24_1_0p76_0"],"t":61,"s":[100],"e":[0]},{"t":68}],"ix":7},"sk":{"a":0,"k":0,"ix":4},"sa":{"a":0,"k":0,"ix":5},"nm":"Transform"}],"nm":"Group 1","np":3,"cix":2,"ix":1,"mn":"ADBE Vector Group","hd":false}],"ip":0,"op":321,"st":0,"bm":0},{"ddd":0,"ind":20,"ty":3,"nm":"Null 4","sr":1,"ks":{"o":{"a":0,"k":0,"ix":11},"r":{"a":0,"k":0,"ix":10},"p":{"a":0,"k":[250,250,0],"ix":2},"a":{"a":0,"k":[0,0,0],"ix":1},"s":{"a":0,"k":[100,100,100],"ix":6}},"ao":0,"ef":[{"ty":5,"nm":"main","np":3,"mn":"ADBE Slider Control","ix":1,"en":1,"ef":[{"ty":0,"nm":"Slider","mn":"ADBE Slider Control-0001","ix":1,"v":{"a":1,"k":[{"i":{"x":[0.16],"y":[1]},"o":{"x":[0.76],"y":[0]},"n":["0p16_1_0p76_0"],"t":8,"s":[0],"e":[100]},{"t":18}],"ix":1}}]},{"ty":5,"nm":"main width","np":3,"mn":"ADBE Slider Control","ix":2,"en":1,"ef":[{"ty":0,"nm":"Slider","mn":"ADBE Slider Control-0001","ix":1,"v":{"a":1,"k":[{"i":{"x":[0.12],"y":[0.86]},"o":{"x":[0.88],"y":[0.14]},"n":["0p12_0p86_0p88_0p14"],"t":10,"s":[0],"e":[26]},{"t":20}],"ix":1}}]},{"ty":5,"nm":"side","np":3,"mn":"ADBE Slider Control","ix":3,"en":1,"ef":[{"ty":0,"nm":"Slider","mn":"ADBE Slider Control-0001","ix":1,"v":{"a":1,"k":[{"i":{"x":[0.16],"y":[1]},"o":{"x":[0.76],"y":[0]},"n":["0p16_1_0p76_0"],"t":11,"s":[0],"e":[100]},{"t":21}],"ix":1}}]},{"ty":5,"nm":"side width","np":3,"mn":"ADBE Slider Control","ix":4,"en":1,"ef":[{"ty":0,"nm":"Slider","mn":"ADBE Slider Control-0001","ix":1,"v":{"a":1,"k":[{"i":{"x":[0.12],"y":[1]},"o":{"x":[0.88],"y":[0]},"n":["0p12_1_0p88_0"],"t":17,"s":[13],"e":[13]},{"t":27}],"ix":1}}]},{"ty":5,"nm":"opacity","np":3,"mn":"ADBE Slider Control","ix":5,"en":1,"ef":[{"ty":0,"nm":"Slider","mn":"ADBE Slider Control-0001","ix":1,"v":{"a":1,"k":[{"i":{"x":[0.16],"y":[1]},"o":{"x":[0.76],"y":[0]},"n":["0p16_1_0p76_0"],"t":11,"s":[100],"e":[100]},{"i":{"x":[0.833],"y":[1]},"o":{"x":[0.167],"y":[0]},"n":["0p833_1_0p167_0"],"t":19,"s":[100],"e":[0]},{"t":27}],"ix":1}}]}],"ip":0,"op":321,"st":0,"bm":0}],"markers":[{"tm":0,"cm":"","dr":0},{"tm":29,"cm":"","dr":0},{"tm":49,"cm":"","dr":0},{"tm":70,"cm":"","dr":0}]}